README
setup.py
bitgo/__init__.py
bitgo/bitgo.py
bitgo/cmd.py
bitgo/sjcl.py
bitgo.egg-info/PKG-INFO
bitgo.egg-info/SOURCES.txt
bitgo.egg-info/dependency_links.txt
bitgo.egg-info/entry_points.txt
bitgo.egg-info/requires.txt
bitgo.egg-info/top_level.txt