Metadata-Version: 1.1
Name: bitgo
Version: 0.1.4
Summary: alpha version of a bitgo python library
Home-page: https://github.com/sserrano44/pybitgo
Author: Sebastian Serrano
Author-email: sebastian@bitpagos.com
License: UNKNOWN
Download-URL: https://github.com/sserrano44/pybitgo/tarball/0.1.4
Keywords: bitcoin,bitgo
Platform: UNKNOWN
Classifier: Programming Language :: Python :: 2.7
Classifier: Topic :: Internet
Classifier: Topic :: Software Development :: Libraries :: Python Modules
